tf_package/__init__.py
tf_package/attention.py
tf_package/gan_loss.py
tf_package/instancenorm.py
tf_package/make_tfrecord.py
tf_package/spectral_norm.py
tf_package/test_data.py
tf_package/utils.py
tf_package-0.0.3.dist-info/METADATA
tf_package-0.0.3.dist-info/WHEEL
tf_package-0.0.3.dist-info/entry_points.txt
tf_package-0.0.3.dist-info/top_level.txt
tf_package-0.0.3.dist-info/RECORD
