Metadata-Version: 2.1
Name: tf-package
Version: 0.0.3
Summary: 增加TensorFlow没有的功能函数
Home-page: https://github.com/yuhe-tf/tf_package
Author: YuHe
Author-email: yuying11130108@gmail.com
License: UNKNOWN
Platform: UNKNOWN
Requires-Python: >=3.6
